robotics_numpy/__init__.py
robotics_numpy/kinematics/__init__.py
robotics_numpy/kinematics/forward.py
robotics_numpy/kinematics/jacobian.py
robotics_numpy/models/__init__.py
robotics_numpy/models/dh_link.py
robotics_numpy/models/dh_robot.py
robotics_numpy/models/generic.py
robotics_numpy/models/stanford.py
robotics_numpy/transforms/__init__.py
robotics_numpy/transforms/homogeneous.py
robotics_numpy/transforms/pose.py
robotics_numpy/transforms/rotations.py
robotics_numpy/visualization/__init__.py
robotics_numpy-0.1.0.dist-info/METADATA
robotics_numpy-0.1.0.dist-info/WHEEL
robotics_numpy-0.1.0.dist-info/licenses/LICENSE
robotics_numpy-0.1.0.dist-info/RECORD
