Metadata-Version: 2.4
Name: robotics-numpy
Version: 0.1.0
Summary: A solely NumPy-dependent robotics Python package for basic kinematics, dynamics, and others.
Author-email: Chaoyue Fei <chaoyue.fei@vub.be>
License-Expression: MIT
License-File: LICENSE
Keywords: dynamics,forward-kinematics,inverse-kinematics,kinematics,lightweight,motion-planning,numpy,robot-manipulator,robotics
Classifier: Development Status :: 3 - Alpha
Classifier: Intended Audience :: Developers
Classifier: Intended Audience :: Education
Classifier: Intended Audience :: Science/Research
Classifier: License :: OSI Approved :: MIT License
Classifier: Operating System :: OS Independent
Classifier: Programming Language :: Python :: 3
Classifier: Programming Language :: Python :: 3.9
Classifier: Programming Language :: Python :: 3.10
Classifier: Programming Language :: Python :: 3.11
Classifier: Programming Language :: Python :: 3.12
Classifier: Topic :: Scientific/Engineering
Classifier: Topic :: Scientific/Engineering :: Mathematics
Classifier: Topic :: Scientific/Engineering :: Physics
Classifier: Topic :: Software Development :: Libraries :: Python Modules
Requires-Python: >=3.9
Requires-Dist: numpy
Provides-Extra: all
Requires-Dist: plotly>=5.0.0; extra == 'all'
Provides-Extra: docs
Requires-Dist: mkdocs-jupyter>=0.24.0; extra == 'docs'
Requires-Dist: mkdocs-material>=9.0.0; extra == 'docs'
Requires-Dist: mkdocstrings[python]>=0.20.0; extra == 'docs'
Provides-Extra: rtb
Requires-Dist: black>=23.0.0; extra == 'rtb'
Requires-Dist: mypy>=1.0.0; extra == 'rtb'
Requires-Dist: plotly; extra == 'rtb'
Requires-Dist: pytest-benchmark>=4.0.0; extra == 'rtb'
Requires-Dist: pytest-cov>=4.0.0; extra == 'rtb'
Requires-Dist: pytest>=7.0.0; extra == 'rtb'
Requires-Dist: roboticstoolbox-python; extra == 'rtb'
Requires-Dist: ruff>=0.1.0; extra == 'rtb'
Provides-Extra: test
Requires-Dist: black; extra == 'test'
Requires-Dist: mypy; extra == 'test'
Requires-Dist: plotly; extra == 'test'
Requires-Dist: pytest; extra == 'test'
Requires-Dist: pytest-benchmark; extra == 'test'
Requires-Dist: pytest-cov; extra == 'test'
Requires-Dist: ruff; extra == 'test'
Provides-Extra: visualization
Requires-Dist: plotly>=5.0.0; extra == 'visualization'
